cqas/__init__.py
cqas/__main__.py
cqas/_colours.py
cqas/_reporter.py
cqas/py.typed
cqas/analysers/__init__.py
cqas/analysers/base.py
cqas/analysers/complexity.py
cqas/analysers/dead_code.py
cqas/analysers/duplication.py
cqas/analysers/full.py
cqas/analysers/halstead.py
cqas/analysers/imports.py
cqas/analysers/pep8.py
cqas/analysers/py.typed
cqas/analysers/readability.py
cqas/analysers/security.py
cqas/constructs/__init__.py
cqas/constructs/classification.py
cqas/constructs/complexity.py
cqas/constructs/dead_code.py
cqas/constructs/duplication.py
cqas/constructs/full.py
cqas/constructs/halstead.py
cqas/constructs/imports.py
cqas/constructs/pep8.py
cqas/constructs/py.typed
cqas/constructs/readability.py
cqas/constructs/security.py
cqas/lang/__init__.py
cqas/lang/en.py
cqas/lang/lt.py
cqas-2.0.0.dist-info/licenses/LICENSE
cqas-2.0.0.dist-info/METADATA
cqas-2.0.0.dist-info/WHEEL
cqas-2.0.0.dist-info/entry_points.txt
cqas-2.0.0.dist-info/top_level.txt
cqas-2.0.0.dist-info/zip-safe
cqas-2.0.0.dist-info/RECORD
