Metadata-Version: 2.4
Name: cqas
Version: 2.0.0
Summary: Python Code Quality and Security (CQaS) tester
Home-page: https://git.ari.lt/ari/cqas
Author: Arija A.
Author-email: ari@ari.lt
License: AGPLv3+
Keywords: quality,security,maintainability,tooling,ci,cybersec,ast,linter
Classifier: Development Status :: 4 - Beta
Classifier: Intended Audience :: Developers
Classifier: License :: OSI Approved :: GNU Affero General Public License v3 or later (AGPLv3+)
Classifier: Operating System :: OS Independent
Classifier: Programming Language :: Python :: 3
Classifier: Programming Language :: Python :: 3.8
Classifier: Programming Language :: Python :: 3.9
Classifier: Programming Language :: Python :: 3.10
Classifier: Programming Language :: Python :: 3.11
Classifier: Programming Language :: Python :: 3.12
Classifier: Programming Language :: Python :: 3.13
Classifier: Topic :: Security
Classifier: Typing :: Typed
License-File: LICENSE
Provides-Extra: colour
Requires-Dist: colorama; extra == "colour"
Dynamic: license-file
